setup.py
plocal/__init__.py
plocal/local.py
plocal.egg-info/PKG-INFO
plocal.egg-info/SOURCES.txt
plocal.egg-info/dependency_links.txt
plocal.egg-info/top_level.txt