Metadata-Version: 1.0
Name: plocal
Version: 0.1
Summary: A "local" storage class that mirrors threading.local but works across multiple processes as well as threads.
Home-page: http://ohthehugemanatee.net/
Author: Dave Mankoff
Author-email: mankyd@gmail.com
License: BSD
Keywords: fork multiprocessing threading local storage
Platform: UNKNOWN
Classifier: Development Status :: 4 - Beta
Classifier: Topic :: Software Development
Classifier: Topic :: Utilities
Classifier: License :: OSI Approved :: BSD License
